fast_poibin/__init__.py
fast_poibin/check_accuracy.py
fast_poibin/pmf.py
fast_poibin/poibin.py
fast_poibin/py.typed
fast_poibin-0.4.0.dist-info/LICENSE
fast_poibin-0.4.0.dist-info/METADATA
fast_poibin-0.4.0.dist-info/WHEEL
fast_poibin-0.4.0.dist-info/RECORD
