Metadata-Version: 2.1
Name: fast-poibin
Version: 0.4.0
Summary: Package for computing PMF and CDF of Poisson binomial distribution.
Home-page: https://github.com/privet-kitty/fast-poibin
License: MPL-2.0
Author: Hugo Sansaqua
Author-email: privet.kitty99@gmail.com
Requires-Python: >=3.9,<4.0
Classifier: License :: OSI Approved
Classifier: Programming Language :: Python :: 3
Classifier: Programming Language :: Python :: 3.9
Classifier: Programming Language :: Python :: 3.10
Classifier: Programming Language :: Python :: 3.11
Classifier: Programming Language :: Python :: 3.12
Requires-Dist: numba (>=0.57,<0.58) ; python_version >= "3.9" and python_version < "3.12"
Requires-Dist: numba (>=0.59,<0.60) ; python_version >= "3.12" and python_version < "3.13"
Requires-Dist: numba (>=0.61,<0.62) ; python_version >= "3.13"
Requires-Dist: numpy (>=1.23)
Project-URL: Documentation, https://privet-kitty.github.io/fast-poibin/
Project-URL: Repository, https://github.com/privet-kitty/fast-poibin
